brambox/__init__.py
brambox/log.py
brambox/boxes/__init__.py
brambox/boxes/box.py
brambox/boxes/formats.py
brambox/boxes/annotations/__init__.py
brambox/boxes/annotations/annotation.py
brambox/boxes/annotations/cvc.py
brambox/boxes/annotations/darknet.py
brambox/boxes/annotations/dollar.py
brambox/boxes/annotations/formats.py
brambox/boxes/annotations/kitti.py
brambox/boxes/annotations/pascalvoc.py
brambox/boxes/annotations/pickle.py
brambox/boxes/annotations/vatic.py
brambox/boxes/annotations/yaml.py
brambox/boxes/detections/__init__.py
brambox/boxes/detections/coco.py
brambox/boxes/detections/detection.py
brambox/boxes/detections/dollar.py
brambox/boxes/detections/formats.py
brambox/boxes/detections/pascalvoc.py
brambox/boxes/detections/pickle.py
brambox/boxes/detections/yaml.py
brambox/boxes/statistics/__init__.py
brambox/boxes/statistics/mr_fppi.py
brambox/boxes/statistics/pr.py
brambox/boxes/statistics/util.py
brambox/boxes/util/__init__.py
brambox/boxes/util/convert.py
brambox/boxes/util/filters.py
brambox/boxes/util/modifiers.py
brambox/boxes/util/path.py
brambox/boxes/util/visual.py
brambox/transforms/__init__.py
brambox/transforms/channelMixer.py
lightnet/__init__.py
lightnet/_version.py
lightnet/log.py
lightnet/data/__init__.py
lightnet/data/_dataloading.py
lightnet/data/transform/__init__.py
lightnet/data/transform/_postprocess.py
lightnet/data/transform/_preprocess.py
lightnet/data/transform/util.py
lightnet/engine/__init__.py
lightnet/engine/_engine.py
lightnet/engine/_parameter.py
lightnet/engine/_scheduler.py
lightnet/engine/_visual.py
lightnet/models/__init__.py
lightnet/models/_dataset_brambox.py
lightnet/models/_dataset_darknet.py
lightnet/models/_network_darknet19.py
lightnet/models/_network_mobilenet_yolo.py
lightnet/models/_network_tiny_yolo.py
lightnet/models/_network_yolo.py
lightnet/network/__init__.py
lightnet/network/layer/__init__.py
lightnet/network/layer/_darknet.py
lightnet/network/layer/_mobilenet.py
lightnet/network/loss/__init__.py
wbia_lightnet-3.0.1.dist-info/LICENSE
wbia_lightnet-3.0.1.dist-info/METADATA
wbia_lightnet-3.0.1.dist-info/WHEEL
wbia_lightnet-3.0.1.dist-info/top_level.txt
wbia_lightnet-3.0.1.dist-info/RECORD
