Metadata-Version: 2.1
Name: wbia-lightnet
Version: 3.0.1
Summary: Building blocks for recreating darknet networks in pytorch
Home-page: UNKNOWN
Author: EAVISE, WildMe Developers
Author-email: dev@wildme.org
License: UNKNOWN
Platform: UNKNOWN
